memorial/__init__.py
memorial/core.py
memorial/utils.py
memorial/replay_buffers/__init__.py
memorial/replay_buffers/flat_replay_buffer.py
memorial/wrappers/__init__.py
memorial/wrappers/dict_wrapper/__init__.py
memorial/wrappers/dict_wrapper/dict_wrapper.py
memorial/wrappers/dict_wrapper/listed_dict_to_dicted_list.py
memorial-0.0.8.dist-info/LICENSE.txt
memorial-0.0.8.dist-info/METADATA
memorial-0.0.8.dist-info/WHEEL
memorial-0.0.8.dist-info/top_level.txt
memorial-0.0.8.dist-info/RECORD
