Metadata-Version: 2.1
Name: memorial
Version: 0.0.8
Summary: Replay Buffer Implementations for RL
Author-email: Jet <taijunjet@hotmail.com>
License: Copyright (c) 2018 The Python Packaging Authority
Project-URL: Homepage, https://github.com/jjshoots/Memorial
Keywords: Machine Learning,Reinforcement Learning
Classifier: Programming Language :: Python :: 3
Classifier: License :: OSI Approved :: MIT License
Classifier: Operating System :: OS Independent
Requires-Python: >=3.10
License-File: LICENSE.txt
Requires-Dist: numpy
Requires-Dist: prefetch-generator
Provides-Extra: dev
Requires-Dist: pytest ; extra == 'dev'
Requires-Dist: pytest-xdist ; extra == 'dev'
Requires-Dist: pre-commit ; extra == 'dev'
Requires-Dist: torch ; extra == 'dev'
